LICENSE.txt
MANIFEST.in
README.rst
setup.py
pycgi/__init__.py
pycgi/pycgi.py
pycgi.egg-info/PKG-INFO
pycgi.egg-info/SOURCES.txt
pycgi.egg-info/dependency_links.txt
pycgi.egg-info/entry_points.txt
pycgi.egg-info/requires.txt
pycgi.egg-info/top_level.txt
pycgi.egg-info/zip-safe
pycgi/config/argparse.txt
pycgi/config/messages.txt
pycgi/config/pycgi.ini