Metadata-Version: 1.1
Name: pycgi
Version: 0.1a3
Summary: The Python CGI administration utility
Home-page: https://github.com/korniichuk/pycgi
Author: Ruslan Korniichuk
Author-email: ruslan.korniichuk@gmail.com
License: Public Domain
Download-URL: https://github.com/korniichuk/pycgi/archive/0.1.zip
Keywords: cgi,cgi installer,pycgi,python cgi,python2
Platform: Linux
Classifier: Development Status :: 3 - Alpha
Classifier: Environment :: Console
Classifier: Intended Audience :: Developers
Classifier: Intended Audience :: Information Technology
Classifier: Intended Audience :: System Administrators
Classifier: License :: Public Domain
Classifier: Operating System :: POSIX :: Linux
Classifier: Programming Language :: Python
Classifier: Programming Language :: Python :: 2
Classifier: Programming Language :: Python :: 2.7
Classifier: Programming Language :: Python :: 2 :: Only
Classifier: Topic :: Internet :: WWW/HTTP :: Dynamic Content :: CGI Tools/Libraries
Classifier: Topic :: System :: Systems Administration
Classifier: Topic :: Utilities
